unfold/__init__.py
unfold/admin.py
unfold/apps.py
unfold/checks.py
unfold/components.py
unfold/dataclasses.py
unfold/datasets.py
unfold/decorators.py
unfold/enums.py
unfold/exceptions.py
unfold/fields.py
unfold/forms.py
unfold/layout.py
unfold/overrides.py
unfold/paginator.py
unfold/sections.py
unfold/settings.py
unfold/sites.py
unfold/typing.py
unfold/utils.py
unfold/views.py
unfold/widgets.py
unfold/contrib/__init__.py
unfold/contrib/constance/__init__.py
unfold/contrib/constance/apps.py
unfold/contrib/constance/settings.py
unfold/contrib/filters/__init__.py
unfold/contrib/filters/apps.py
unfold/contrib/filters/forms.py
unfold/contrib/filters/admin/__init__.py
unfold/contrib/filters/admin/autocomplete_filters.py
unfold/contrib/filters/admin/choice_filters.py
unfold/contrib/filters/admin/datetime_filters.py
unfold/contrib/filters/admin/dropdown_filters.py
unfold/contrib/filters/admin/mixins.py
unfold/contrib/filters/admin/numeric_filters.py
unfold/contrib/filters/admin/text_filters.py
unfold/contrib/forms/__init__.py
unfold/contrib/forms/apps.py
unfold/contrib/forms/widgets.py
unfold/contrib/guardian/__init__.py
unfold/contrib/guardian/apps.py
unfold/contrib/import_export/__init__.py
unfold/contrib/import_export/apps.py
unfold/contrib/import_export/forms.py
unfold/contrib/inlines/__init__.py
unfold/contrib/inlines/admin.py
unfold/contrib/inlines/apps.py
unfold/contrib/inlines/checks.py
unfold/contrib/inlines/forms.py
unfold/contrib/location_field/__init__.py
unfold/contrib/location_field/apps.py
unfold/contrib/simple_history/__init__.py
unfold/contrib/simple_history/apps.py
unfold/mixins/__init__.py
unfold/mixins/action_model_admin.py
unfold/mixins/base_model_admin.py
unfold/mixins/dataset_model_admin.py
unfold/templatetags/__init__.py
unfold/templatetags/unfold.py
unfold/templatetags/unfold_list.py
django_unfold_conf-0.71.4.dist-info/METADATA
django_unfold_conf-0.71.4.dist-info/WHEEL
django_unfold_conf-0.71.4.dist-info/top_level.txt
django_unfold_conf-0.71.4.dist-info/RECORD
