Metadata-Version: 2.1
Name: django-unfold-conf
Version: 0.71.4
Summary: This is a package forked from https://unfoldadmin.com/ that I make some adjustments, earby I fully credit the original author.
